registration/__init__.py
registration/registration.py
unit_testing_best_practice/__init__.py
unit_testing_best_practice/sample.py
dsti_mlops_labs_egjfour-0.0.1.dist-info/LICENSE
dsti_mlops_labs_egjfour-0.0.1.dist-info/METADATA
dsti_mlops_labs_egjfour-0.0.1.dist-info/WHEEL
dsti_mlops_labs_egjfour-0.0.1.dist-info/top_level.txt
dsti_mlops_labs_egjfour-0.0.1.dist-info/RECORD
